{
  "doc_id": "8440",
  "title": "2021 Sales Tax Newsletter - 3rd Quarter",
  "pages": 2,
  "words": 882,
  "chars": 5966,
  "first_page_excerpt": "www.hdlcompanies.com | 888.861.0220\nQ3 2020*\nQ3 2021*\nLegend\n$0\n$200,000\n$400,000\n$600,000\n$800,000\n$1,000,000\n$1,200,000\n$1,400,000\n$1,600,000\nSALES TAX BY MAJOR BUSINESS GROUP\n*Allocation aberrations have been adjusted to reflect sales activity\nGeneral\nConsumer\nGoods\nCounty\nand State\nPools\nRestaurants\nand\nHotels\nFuel and\nService\nStations\nBuilding\nand\nConstruction\nBusiness\nand\nIndustry\nAutos\nand\nTransportation\nFood\nand\nDrugs\nTOP 25 PRODUCERS\nCITY OF OCEANSIDE HIGHLIGHTS\nPublished by HdL Companies in Winter 2022\nAlbertsons\nBest Buy\nChevron\nChick Fil A\nCircle K\nCVS Pharmacy\nDiscount Fuel\nExpress Fuel\nG&M\nHome Depot\nIn N Out Burger\nKohls\nKrannich Solar West\nLowes\nMcDonald\u2019s\nMelrose Shell\nMohsen Oil\nMossy Nissan\nNew Flyer of America\nRoss\nSuperior Ready Mix\nTarget\nTJ Maxx\nUnited Oil\nWalmart Su"
}